sphinxcontrib_openapi-0.8.3-py3.11-nspkg.pth
sphinxcontrib/openapi/__init__.py
sphinxcontrib/openapi/__main__.py
sphinxcontrib/openapi/_lib2to3.py
sphinxcontrib/openapi/directive.py
sphinxcontrib/openapi/openapi20.py
sphinxcontrib/openapi/openapi30.py
sphinxcontrib/openapi/openapi31.py
sphinxcontrib/openapi/schema_utils.py
sphinxcontrib/openapi/utils.py
sphinxcontrib/openapi/renderers/__init__.py
sphinxcontrib/openapi/renderers/_httpdomain.py
sphinxcontrib/openapi/renderers/_httpdomain_old.py
sphinxcontrib/openapi/renderers/abc.py
sphinxcontrib_openapi-0.8.3.dist-info/LICENSE
sphinxcontrib_openapi-0.8.3.dist-info/METADATA
sphinxcontrib_openapi-0.8.3.dist-info/WHEEL
sphinxcontrib_openapi-0.8.3.dist-info/namespace_packages.txt
sphinxcontrib_openapi-0.8.3.dist-info/top_level.txt
sphinxcontrib_openapi-0.8.3.dist-info/RECORD
